aliyunsdkidaas_doraemon/__init__.py
aliyunsdkidaas_doraemon/endpoint.py
aliyunsdkidaas_doraemon/request/__init__.py
aliyunsdkidaas_doraemon/request/v20210520/CreateAuthenticatorRegistrationRequest.py
aliyunsdkidaas_doraemon/request/v20210520/CreateUserAuthenticateOptionsRequest.py
aliyunsdkidaas_doraemon/request/v20210520/DeregisterAuthenticatorRequest.py
aliyunsdkidaas_doraemon/request/v20210520/FetchAccessTokenRequest.py
aliyunsdkidaas_doraemon/request/v20210520/GetAuthenticatorRequest.py
aliyunsdkidaas_doraemon/request/v20210520/ListAuthenticationLogsRequest.py
aliyunsdkidaas_doraemon/request/v20210520/ListAuthenticatorOpsLogsRequest.py
aliyunsdkidaas_doraemon/request/v20210520/ListAuthenticatorsRequest.py
aliyunsdkidaas_doraemon/request/v20210520/ListCostUnitOrdersRequest.py
aliyunsdkidaas_doraemon/request/v20210520/ListOrderConsumeStatisticRecordsRequest.py
aliyunsdkidaas_doraemon/request/v20210520/ListPwnedPasswordsRequest.py
aliyunsdkidaas_doraemon/request/v20210520/ListUsersRequest.py
aliyunsdkidaas_doraemon/request/v20210520/QuerySmsReportsRequest.py
aliyunsdkidaas_doraemon/request/v20210520/QuerySmsUpsRequest.py
aliyunsdkidaas_doraemon/request/v20210520/RegisterAuthenticatorRequest.py
aliyunsdkidaas_doraemon/request/v20210520/ServiceInvokeRequest.py
aliyunsdkidaas_doraemon/request/v20210520/UpdateAuthenticatorAttributeRequest.py
aliyunsdkidaas_doraemon/request/v20210520/VerifyIdTokenRequest.py
aliyunsdkidaas_doraemon/request/v20210520/VerifyUserAuthenticationRequest.py
aliyunsdkidaas_doraemon/request/v20210520/__init__.py
aliyun_python_sdk_idaas_doraemon-1.0.1.dist-info/LICENSE
aliyun_python_sdk_idaas_doraemon-1.0.1.dist-info/METADATA
aliyun_python_sdk_idaas_doraemon-1.0.1.dist-info/WHEEL
aliyun_python_sdk_idaas_doraemon-1.0.1.dist-info/top_level.txt
aliyun_python_sdk_idaas_doraemon-1.0.1.dist-info/RECORD
